<?xml version="1.0" encoding="UTF-8"?>
<ensemble>
	<tree id="1" weight="0.1">
		<split>
			<feature> 58 </feature>
			<threshold> 0.5482442 </threshold>
			<split pos="left">
				<feature> 7 </feature>
				<threshold> 0.046875 </threshold>
				<split pos="left">
					<output> 0.0014297969 </output>
				</split>
				<split pos="right">
					<feature> 58 </feature>
					<threshold> 0.38007236 </threshold>
					<split pos="left">
						<output> 0.0 </output>
					</split>
					<split pos="right">
						<feature> 57 </feature>
						<threshold> 0.98828125 </threshold>
						<split pos="left">
							<feature> 40 </feature>
							<threshold> 0.8769573 </threshold>
							<split pos="left">
								<feature> 6 </feature>
								<threshold> 0.042394016 </threshold>
								<split pos="left">
									<output> 1.9293479 </output>
								</split>
								<split pos="right">
									<output> 3.0384614 </output>
								</split>
							</split>
							<split pos="right">
								<output> 7.0 </output>
							</split>
						</split>
						<split pos="right">
							<feature> 24 </feature>
							<threshold> 0.8108189 </threshold>
							<split pos="left">
								<output> 1.4983922 </output>
							</split>
							<split pos="right">
								<output> 4.0 </output>
							</split>
						</split>
					</split>
				</split>
			</split>
			<split pos="right">
				<feature> 15 </feature>
				<threshold> 0.0 </threshold>
				<split pos="left">
					<output> 0.0 </output>
				</split>
				<split pos="right">
					<feature> 33 </feature>
					<threshold> 0.0 </threshold>
					<split pos="left">
						<output> 0.0 </output>
					</split>
					<split pos="right">
						<feature> 1 </feature>
						<threshold> 0.6 </threshold>
						<split pos="left">
							<feature> 56 </feature>
							<threshold> 0.078125 </threshold>
							<split pos="left">
								<feature> 22 </feature>
								<threshold> 0.13636413 </threshold>
								<split pos="left">
									<output> 4.0 </output>
								</split>
								<split pos="right">
									<feature> 62 </feature>
									<threshold> 0.51171875 </threshold>
									<split pos="left">
										<feature> 30 </feature>
										<threshold> 0.41796875 </threshold>
										<split pos="left">
											<output> 2.3479729 </output>
										</split>
										<split pos="right">
											<feature> 60 </feature>
											<threshold> 0.01569603 </threshold>
											<split pos="left">
												<feature> 65 </feature>
												<threshold> 0.5078125 </threshold>
												<split pos="left">
													<output> 1.7590909 </output>
												</split>
												<split pos="right">
													<feature> 4 </feature>
													<threshold> 0.0025445293 </threshold>
													<split pos="left">
														<feature> 42 </feature>
														<threshold> 0.031160433 </threshold>
														<split pos="left">
															<output> 2.109375 </output>
														</split>
														<split pos="right">
															<feature> 45 </feature>
															<threshold> 0.93598974 </threshold>
															<split pos="left">
																<output> 2.189655 </output>
															</split>
															<split pos="right">
																<feature> 1 </feature>
																<threshold> 0.45185184 </threshold>
																<split pos="left">
																	<feature> 27 </feature>
																	<threshold> 0.7299273 </threshold>
																	<split pos="left">
																		<output> 3.1910112 </output>
																	</split>
																	<split pos="right">
																		<output> 1.5 </output>
																	</split>
																</split>
																<split pos="right">
																	<output> 5.2222223 </output>
																</split>
															</split>
														</split>
													</split>
													<split pos="right">
														<output> 1.7872341 </output>
													</split>
												</split>
											</split>
											<split pos="right">
												<feature> 58 </feature>
												<threshold> 0.9307551 </threshold>
												<split pos="left">
													<feature> 46 </feature>
													<threshold> 0.036382996 </threshold>
													<split pos="left">
														<output> 2.4070797 </output>
													</split>
													<split pos="right">
														<output> 5.4 </output>
													</split>
												</split>
												<split pos="right">
													<feature> 58 </feature>
													<threshold> 0.9934077 </threshold>
													<split pos="left">
														<feature> 42 </feature>
														<threshold> 0.058858592 </threshold>
														<split pos="left">
															<feature> 23 </feature>
															<threshold> 0.6916597 </threshold>
															<split pos="left">
																<output> 1.6916996 </output>
															</split>
															<split pos="right">
																<output> 2.06875 </output>
															</split>
														</split>
														<split pos="right">
															<output> 2.3947368 </output>
														</split>
													</split>
													<split pos="right">
														<output> 1.5015479 </output>
													</split>
												</split>
											</split>
										</split>
									</split>
									<split pos="right">
										<feature> 58 </feature>
										<threshold> 0.8549124 </threshold>
										<split pos="left">
											<output> 2.6190476 </output>
										</split>
										<split pos="right">
											<feature> 30 </feature>
											<threshold> 0.84375 </threshold>
											<split pos="left">
												<output> 2.13 </output>
											</split>
											<split pos="right">
												<output> 1.3795455 </output>
											</split>
										</split>
									</split>
								</split>
							</split>
							<split pos="right">
								<feature> 65 </feature>
								<threshold> 0.95703125 </threshold>
								<split pos="left">
									<feature> 17 </feature>
									<threshold> 0.8891111 </threshold>
									<split pos="left">
										<feature> 58 </feature>
										<threshold> 0.66695446 </threshold>
										<split pos="left">
											<feature> 30 </feature>
											<threshold> 0.53125 </threshold>
											<split pos="left">
												<feature> 51 </feature>
												<threshold> 0.959596 </threshold>
												<split pos="left">
													<feature> 7 </feature>
													<threshold> 0.015625 </threshold>
													<split pos="left">
														<output> 2.7 </output>
													</split>
													<split pos="right">
														<feature> 51 </feature>
														<threshold> 0.3131313 </threshold>
														<split pos="left">
															<output> 1.5581396 </output>
														</split>
														<split pos="right">
															<feature> 55 </feature>
															<threshold> 0.05464473 </threshold>
															<split pos="left">
																<feature> 64 </feature>
																<threshold> 0.328125 </threshold>
																<split pos="left">
																	<feature> 22 </feature>
																	<threshold> 0.83917356 </threshold>
																	<split pos="left">
																		<feature> 49 </feature>
																		<threshold> 0.013212509 </threshold>
																		<split pos="left">
																			<feature> 13 </feature>
																			<threshold> 0.026010655 </threshold>
																			<split pos="left">
																				<output> 2.1549296 </output>
																			</split>
																			<split pos="right">
																				<feature> 46 </feature>
																				<threshold> 0.02228269 </threshold>
																				<split pos="left">
																					<output> 1.6852459 </output>
																				</split>
																				<split pos="right">
																					<output> 1.8994975 </output>
																				</split>
																			</split>
																		</split>
																		<split pos="right">
																			<feature> 53 </feature>
																			<threshold> 0.63806397 </threshold>
																			<split pos="left">
																				<feature> 56 </feature>
																				<threshold> 0.10546875 </threshold>
																				<split pos="left">
																					<output> 1.5882353 </output>
																				</split>
																				<split pos="right">
																					<feature> 18 </feature>
																					<threshold> 0.53037596 </threshold>
																					<split pos="left">
																						<output> 2.9583333 </output>
																					</split>
																					<split pos="right">
																						<feature> 36 </feature>
																						<threshold> 0.20878509 </threshold>
																						<split pos="left">
																							<feature> 44 </feature>
																							<threshold> 0.027493972 </threshold>
																							<split pos="left">
																								<output> 5.0 </output>
																							</split>
																							<split pos="right">
																								<feature> 49 </feature>
																								<threshold> 0.013315251 </threshold>
																								<split pos="left">
																									<output> 3.2 </output>
																								</split>
																								<split pos="right">
																									<output> 2.1058202 </output>
																								</split>
																							</split>
																						</split>
																						<split pos="right">
																							<output> 6.0 </output>
																						</split>
																					</split>
																				</split>
																			</split>
																			<split pos="right">
																				<output> 1.6637168 </output>
																			</split>
																		</split>
																	</split>
																	<split pos="right">
																		<feature> 23 </feature>
																		<threshold> 0.7325328 </threshold>
																		<split pos="left">
																			<feature> 49 </feature>
																			<threshold> 0.0036575843 </threshold>
																			<split pos="left">
																				<output> 2.5555556 </output>
																			</split>
																			<split pos="right">
																				<output> 1.7791798 </output>
																			</split>
																		</split>
																		<split pos="right">
																			<output> 1.6086956 </output>
																		</split>
																	</split>
																</split>
																<split pos="right">
																	<output> 2.3181818 </output>
																</split>
															</split>
															<split pos="right">
																<output> 2.0812182 </output>
															</split>
														</split>
													</split>
												</split>
												<split pos="right">
													<output> 1.6233184 </output>
												</split>
											</split>
											<split pos="right">
												<output> 2.857143 </output>
											</split>
										</split>
										<split pos="right">
											<feature> 27 </feature>
											<threshold> 0.438993 </threshold>
											<split pos="left">
												<output> 5.142857 </output>
											</split>
											<split pos="right">
												<feature> 5 </feature>
												<threshold> 0.0390625 </threshold>
												<split pos="left">
													<feature> 58 </feature>
													<threshold> 0.82853234 </threshold>
													<split pos="left">
														<feature> 32 </feature>
														<threshold> 0.234375 </threshold>
														<split pos="left">
															<feature> 65 </feature>
															<threshold> 0.75 </threshold>
															<split pos="left">
																<feature> 58 </feature>
																<threshold> 0.75268966 </threshold>
																<split pos="left">
																	<feature> 57 </feature>
																	<threshold> 0.9609375 </threshold>
																	<split pos="left">
																		<output> 1.6019901 </output>
																	</split>
																	<split pos="right">
																		<output> 2.3675213 </output>
																	</split>
																</split>
																<split pos="right">
																	<feature> 19 </feature>
																	<threshold> 0.84375 </threshold>
																	<split pos="left">
																		<output> 1.7222222 </output>
																	</split>
																	<split pos="right">
																		<output> 1.4985915 </output>
																	</split>
																</split>
															</split>
															<split pos="right">
																<output> 3.8181818 </output>
															</split>
														</split>
														<split pos="right">
															<feature> 30 </feature>
															<threshold> 0.3984375 </threshold>
															<split pos="left">
																<output> 2.528302 </output>
															</split>
															<split pos="right">
																<feature> 28 </feature>
																<threshold> 0.4119832 </threshold>
																<split pos="left">
																	<output> 2.9615386 </output>
																</split>
																<split pos="right">
																	<feature> 38 </feature>
																	<threshold> 0.8682926 </threshold>
																	<split pos="left">
																		<feature> 58 </feature>
																		<threshold> 0.7329046 </threshold>
																		<split pos="left">
																			<output> 3.0 </output>
																		</split>
																		<split pos="right">
																			<feature> 54 </feature>
																			<threshold> 0.043889195 </threshold>
																			<split pos="left">
																				<output> 2.113744 </output>
																			</split>
																			<split pos="right">
																				<output> 1.5263158 </output>
																			</split>
																		</split>
																	</split>
																	<split pos="right">
																		<output> 1.5930233 </output>
																	</split>
																</split>
															</split>
														</split>
													</split>
													<split pos="right">
														<feature> 33 </feature>
														<threshold> 0.011111111 </threshold>
														<split pos="left">
															<feature> 52 </feature>
															<threshold> 0.023884848 </threshold>
															<split pos="left">
																<feature> 61 </feature>
																<threshold> 0.017024294 </threshold>
																<split pos="left">
																	<feature> 22 </feature>
																	<threshold> 0.57644105 </threshold>
																	<split pos="left">
																		<output> 4.0 </output>
																	</split>
																	<split pos="right">
																		<feature> 23 </feature>
																		<threshold> 0.82685536 </threshold>
																		<split pos="left">
																			<feature> 47 </feature>
																			<threshold> 0.027706336 </threshold>
																			<split pos="left">
																				<output> 1.5201005 </output>
																			</split>
																			<split pos="right">
																				<feature> 35 </feature>
																				<threshold> 0.15625 </threshold>
																				<split pos="left">
																					<feature> 26 </feature>
																					<threshold> 0.0 </threshold>
																					<split pos="left">
																						<output> 3.3333333 </output>
																					</split>
																					<split pos="right">
																						<feature> 48 </feature>
																						<threshold> 0.17687958 </threshold>
																						<split pos="left">
																							<output> 1.6962366 </output>
																						</split>
																						<split pos="right">
																							<output> 2.4 </output>
																						</split>
																					</split>
																				</split>
																				<split pos="right">
																					<output> 2.2195122 </output>
																				</split>
																			</split>
																		</split>
																		<split pos="right">
																			<output> 2.6666667 </output>
																		</split>
																	</split>
																</split>
																<split pos="right">
																	<feature> 30 </feature>
																	<threshold> 0.40234375 </threshold>
																	<split pos="left">
																		<output> 1.7147148 </output>
																	</split>
																	<split pos="right">
																		<feature> 57 </feature>
																		<threshold> 0.74609375 </threshold>
																		<split pos="left">
																			<output> 3.2 </output>
																		</split>
																		<split pos="right">
																			<feature> 57 </feature>
																			<threshold> 0.9765625 </threshold>
																			<split pos="left">
																				<feature> 49 </feature>
																				<threshold> 0.031931944 </threshold>
																				<split pos="left">
																					<feature> 13 </feature>
																					<threshold> 6.2676275E-4 </threshold>
																					<split pos="left">
																						<feature> 63 </feature>
																						<threshold> 0.5625 </threshold>
																						<split pos="left">
																							<feature> 53 </feature>
																							<threshold> 0.84318715 </threshold>
																							<split pos="left">
																								<output> 1.400359 </output>
																							</split>
																							<split pos="right">
																								<output> 2.1666667 </output>
																							</split>
																						</split>
																						<split pos="right">
																							<output> 2.5 </output>
																						</split>
																					</split>
																					<split pos="right">
																						<output> 1.6802721 </output>
																					</split>
																				</split>
																				<split pos="right">
																					<output> 1.1458334 </output>
																				</split>
																			</split>
																			<split pos="right">
																				<output> 1.6424242 </output>
																			</split>
																		</split>
																	</split>
																</split>
															</split>
															<split pos="right">
																<output> 4.0 </output>
															</split>
														</split>
														<split pos="right">
															<output> 1.8526012 </output>
														</split>
													</split>
												</split>
												<split pos="right">
													<feature> 57 </feature>
													<threshold> 0.98828125 </threshold>
													<split pos="left">
														<feature> 51 </feature>
														<threshold> 0.18181819 </threshold>
														<split pos="left">
															<output> 3.0 </output>
														</split>
														<split pos="right">
															<feature> 25 </feature>
															<threshold> 0.78679574 </threshold>
															<split pos="left">
																<feature> 25 </feature>
																<threshold> 0.7785957 </threshold>
																<split pos="left">
																	<feature> 13 </feature>
																	<threshold> 0.0034471953 </threshold>
																	<split pos="left">
																		<output> 2.3076923 </output>
																	</split>
																	<split pos="right">
																		<feature> 39 </feature>
																		<threshold> 0.2890625 </threshold>
																		<split pos="left">
																			<feature> 27 </feature>
																			<threshold> 0.76189804 </threshold>
																			<split pos="left">
																				<feature> 30 </feature>
																				<threshold> 0.453125 </threshold>
																				<split pos="left">
																					<output> 1.575179 </output>
																				</split>
																				<split pos="right">
																					<output> 1.3471074 </output>
																				</split>
																			</split>
																			<split pos="right">
																				<output> 2.3333333 </output>
																			</split>
																		</split>
																		<split pos="right">
																			<output> 3.6666667 </output>
																		</split>
																	</split>
																</split>
																<split pos="right">
																	<output> 3.5 </output>
																</split>
															</split>
															<split pos="right">
																<output> 1.3774104 </output>
															</split>
														</split>
													</split>
													<split pos="right">
														<output> 1.7410257 </output>
													</split>
												</split>
											</split>
										</split>
									</split>
									<split pos="right">
										<output> 11.0 </output>
									</split>
								</split>
								<split pos="right">
									<output> 1.3541666 </output>
								</split>
							</split>
						</split>
						<split pos="right">
							<feature> 29 </feature>
							<threshold> 0.03125 </threshold>
							<split pos="left">
								<feature> 1 </feature>
								<threshold> 0.6074074 </threshold>
								<split pos="left">
									<feature> 4 </feature>
									<threshold> 0.0050890585 </threshold>
									<split pos="left">
										<feature> 40 </feature>
										<threshold> 0.66868025 </threshold>
										<split pos="left">
											<output> 8.0 </output>
										</split>
										<split pos="right">
											<output> 2.8421052 </output>
										</split>
									</split>
									<split pos="right">
										<feature> 68 </feature>
										<threshold> 0.09082431 </threshold>
										<split pos="left">
											<output> 3.5714285 </output>
										</split>
										<split pos="right">
											<output> 12.0 </output>
										</split>
									</split>
								</split>
								<split pos="right">
									<feature> 37 </feature>
									<threshold> 0.28495502 </threshold>
									<split pos="left">
										<feature> 3 </feature>
										<threshold> 0.75 </threshold>
										<split pos="left">
											<output> 1.7344633 </output>
										</split>
										<split pos="right">
											<feature> 59 </feature>
											<threshold> 0.5 </threshold>
											<split pos="left">
												<output> 1.6666666 </output>
											</split>
											<split pos="right">
												<feature> 38 </feature>
												<threshold> 0.8972036 </threshold>
												<split pos="left">
													<output> 3.5333333 </output>
												</split>
												<split pos="right">
													<output> 8.0 </output>
												</split>
											</split>
										</split>
									</split>
									<split pos="right">
										<output> 9.0 </output>
									</split>
								</split>
							</split>
							<split pos="right">
								<feature> 17 </feature>
								<threshold> 0.7000371 </threshold>
								<split pos="left">
									<feature> 25 </feature>
									<threshold> 0.6528616 </threshold>
									<split pos="left">
										<output> 2.0 </output>
									</split>
									<split pos="right">
										<output> 1.6113538 </output>
									</split>
								</split>
								<split pos="right">
									<feature> 68 </feature>
									<threshold> 0.123521045 </threshold>
									<split pos="left">
										<feature> 58 </feature>
										<threshold> 0.7625822 </threshold>
										<split pos="left">
											<output> 2.6666667 </output>
										</split>
										<split pos="right">
											<output> 1.4074074 </output>
										</split>
									</split>
									<split pos="right">
										<output> 11.0 </output>
									</split>
								</split>
							</split>
						</split>
					</split>
				</split>
			</split>
		</split>
	</tree>
</ensemble>
